gradio_consilium_roundtable/__init__.py
gradio_consilium_roundtable/consilium_roundtable.py
gradio_consilium_roundtable/consilium_roundtable.pyi
gradio_consilium_roundtable/templates/component/index.js
gradio_consilium_roundtable/templates/component/style.css
gradio_consilium_roundtable/templates/example/index.js
gradio_consilium_roundtable/templates/example/style.css
gradio_consilium_roundtable-0.0.6.dist-info/METADATA
gradio_consilium_roundtable-0.0.6.dist-info/WHEEL
gradio_consilium_roundtable-0.0.6.dist-info/RECORD
